dyslexic_readability/__init__.py
dyslexic_readability/dyslexic_scores.py
dyslexic_readability/example.py
dyslexic_readability/readability_scores.py
dyslexic_readability/utils.py
dyslexic_readability-0.0.10.dist-info/LICENSE
dyslexic_readability-0.0.10.dist-info/METADATA
dyslexic_readability-0.0.10.dist-info/WHEEL
dyslexic_readability-0.0.10.dist-info/top_level.txt
dyslexic_readability-0.0.10.dist-info/RECORD
