Metadata-Version: 2.1
Name: dyslexic-readability
Version: 0.0.10
Summary: A readability scoring library tailored to the specific needs of Turkish dyslexic readers.
Home-page: https://github.com/AkinGunduz/dyslexic_readability_index
Author: Akin Gunduz
Author-email: akngndz93@gmail.com
Project-URL: Bug Tracker, https://github.com/AkinGunduz/dyslexic_readability_index/issues
Classifier: Programming Language :: Python :: 3
Classifier: License :: OSI Approved :: MIT License
Classifier: Operating System :: OS Independent
Requires-Python: >=3.6
License-File: LICENSE
Requires-Dist: numpy
Requires-Dist: nltk
Requires-Dist: editdistance
